requiembot/__init__.py
requiembot/__main__.py
requiembot/exprs.py
requiembot/lexer.py
requiembot/parser.py
requiembot-0.2.1.dist-info/METADATA
requiembot-0.2.1.dist-info/WHEEL
requiembot-0.2.1.dist-info/licenses/COPYING.md
requiembot-0.2.1.dist-info/RECORD
