Metadata-Version: 2.1
Name: RequiemBot
Version: 0.2.1
Summary: A simple tabletop RPG dice bot for Discord.
Project-URL: Homepage, https://github.com/michaelmunzer/RequiemBot
Author-email: Michael Munzer <michael.munzer@rutgers.edu>
License-File: COPYING.md
Classifier: Development Status :: 4 - Beta
Classifier: Intended Audience :: End Users/Desktop
Classifier: License :: OSI Approved :: GNU Affero General Public License v3 or later (AGPLv3+)
Classifier: Natural Language :: English
Classifier: Operating System :: OS Independent
Classifier: Programming Language :: Python :: 3
Classifier: Programming Language :: Python :: 3.10
Classifier: Topic :: Communications :: Chat
Classifier: Topic :: Games/Entertainment :: Board Games
Classifier: Topic :: Games/Entertainment :: Role-Playing
Requires-Python: >=3.10
Requires-Dist: discord-py
